Doozer-1.2.0.dist-info/DESCRIPTION.rst
Doozer-1.2.0.dist-info/METADATA
Doozer-1.2.0.dist-info/RECORD
Doozer-1.2.0.dist-info/WHEEL
Doozer-1.2.0.dist-info/entry_points.txt
Doozer-1.2.0.dist-info/metadata.json
Doozer-1.2.0.dist-info/top_level.txt
doozer/__init__.py
doozer/__main__.py
doozer/base.py
doozer/cli.py
doozer/config.py
doozer/exceptions.py
doozer/extensions.py
doozer/contrib/__init__.py
doozer/contrib/retry/__init__.py
doozer/contrib/sphinx/__init__.py
